{
  "timestamp": "2026-02-03T08:47:57.467156",
  "markets": [
    {
      "id": "12",
      "name": "Will Joe Biden get Coronavirus before the election?",
      "bid": 0.0,
      "ask": 1.0,
      "spread": 200.0,
      "volume_24h": 0.0,
      "volume_7d": 0.0,
      "liquidity": 0.0,
      "image": "https://polymarket-upload.s3.us-east-2.amazonaws.com/will-joe-biden-get-coronavirus-before-the-election-5a3d4c3b-0a73-419e-a686-be034d2c73ac.png"
    },
    {
      "id": "17",
      "name": "Will Airbnb begin publicly trading before Jan 1, 2021?",
      "bid": 0.0,
      "ask": 1.0,
      "spread": 200.0,
      "volume_24h": 0.0,
      "volume_7d": 0.0,
      "liquidity": 0.0,
      "image": "https://polymarket-upload.s3.us-east-2.amazonaws.com/will-airbnb-begin-publicly-trading-before-jan-1-2021-c1ba5f2f-c025-486a-9664-15cd8d4ac91b.png"
    },
    {
      "id": "18",
      "name": "Will a new Supreme Court Justice be confirmed before Nov 3rd, 2020?",
      "bid": 0.0,
      "ask": 1.0,
      "spread": 200.0,
      "volume_24h": 0.0,
      "volume_7d": 0.0,
      "liquidity": 0.0,
      "image": "https://polymarket-upload.s3.us-east-2.amazonaws.com/will-a-new-supreme-court-justice-be-confirmed-before-nov-3rd-2020-9799dac2-a822-41bf-909a-cdc8eee8ec3e.png"
    },
    {
      "id": "19",
      "name": "Will Kim Kardashian and Kanye West divorce before Jan 1, 2021?",
      "bid": 0.0,
      "ask": 1.0,
      "spread": 200.0,
      "volume_24h": 0.0,
      "volume_7d": 0.0,
      "liquidity": 0.179651,
      "image": "https://polymarket-upload.s3.us-east-2.amazonaws.com/will-kim-kardashian-and-kanye-west-divorce-before-jan-1-2021-56c39e78-0a04-4827-bf52-d2c1052f82d9.png"
    },
    {
      "id": "20",
      "name": "Will Coinbase begin publicly trading before Jan 1, 2021?",
      "bid": 0.0,
      "ask": 1.0,
      "spread": 200.0,
      "volume_24h": 0.0,
      "volume_7d": 0.0,
      "liquidity": 0.367501,
      "image": "https://polymarket-upload.s3.us-east-2.amazonaws.com/will-coinbase-begin-publicly-trading-before-jan-1-2021-e5b376bc-2213-4c84-b0f5-0a53b389402e.png"
    },
    {
      "id": "36",
      "name": "What will the price of Bitcoin be on November 4th, 2020?",
      "bid": 0.0,
      "ask": 1.0,
      "spread": 200.0,
      "volume_24h": 0.0,
      "volume_7d": 0.0,
      "liquidity": 0.0,
      "image": "https://polymarket-upload.s3.us-east-2.amazonaws.com/what-will-the-price-of-bitcoin-be-on-november-4th-2020-b8164552-6f9f-4285-b133-37f6fb04adc3.png"
    },
    {
      "id": "40",
      "name": "Will Trump win the 2020 U.S. presidential election?",
      "bid": 0.0,
      "ask": 1.0,
      "spread": 200.0,
      "volume_24h": 0.0,
      "volume_7d": 0.0,
      "liquidity": 68.283267,
      "image": "https://polymarket-upload.s3.us-east-2.amazonaws.com/will-trump-win-the-2020-us-presidential-election-f67bb1b7-7687-4dd6-bb7b-c5f1a11f9bce.png"
    },
    {
      "id": "42",
      "name": "Will there be an Emergency Use Authorization (EUA) granted for a COVID-19 vaccine prior to Nov 3 2020?",
      "bid": 0.0,
      "ask": 1.0,
      "spread": 200.0,
      "volume_24h": 0.0,
      "volume_7d": 0.0,
      "liquidity": 0.0,
      "image": "https://polymarket-upload.s3.us-east-2.amazonaws.com/will-there-be-an-emergency-use-authorization-eua-granted-for-a-covid-19-vaccine-prior-to-nov-3-2020-bab0b9ba-d7c9-44fd-8307-0cdaf1f12a2e.png"
    },
    {
      "id": "43",
      "name": "What will the total value locked (TVL) in DeFi be at the end of 2020, according to DefiPulse?",
      "bid": 0.0,
      "ask": 1.0,
      "spread": 200.0,
      "volume_24h": 0.0,
      "volume_7d": 0.0,
      "liquidity": 4.601742,
      "image": "https://polymarket-upload.s3.us-east-2.amazonaws.com/what-will-the-total-value-locked-tvl-in-defi-be-at-the-end-of-2020-according-to-defipulse-b42d02b7-1440-4604-83f3-5368d1b51f61.png"
    },
    {
      "id": "44",
      "name": "What will the USD price of Filecoin ($FIL) be on November 17th, 2020?",
      "bid": 0.0,
      "ask": 1.0,
      "spread": 200.0,
      "volume_24h": 0.0,
      "volume_7d": 0.0,
      "liquidity": 190.134841,
      "image": "https://polymarket-upload.s3.us-east-2.amazonaws.com/what-will-the-usd-price-of-filecoin-fil-be-on-november-17th-2020-ea15dbd2-fb55-4de9-b493-25a52e2e89e1.png"
    },
    {
      "id": "46",
      "name": "Will Drake release a new studio album before the end of 2020?",
      "bid": 0.0,
      "ask": 1.0,
      "spread": 200.0,
      "volume_24h": 0.0,
      "volume_7d": 0.0,
      "liquidity": 0.0,
      "image": "https://polymarket-upload.s3.us-east-2.amazonaws.com/will-drake-release-a-new-studio-album-before-the-end-of-2020-5ea30cee-f371-4c91-b421-3cb7f2f5bee9.png"
    },
    {
      "id": "47",
      "name": "Which party will win Florida in the 2020 presidential election?",
      "bid": 0.0,
      "ask": 1.0,
      "spread": 200.0,
      "volume_24h": 0.0,
      "volume_7d": 0.0,
      "liquidity": 0.0,
      "image": "https://polymarket-upload.s3.us-east-2.amazonaws.com/which-party-will-win-florida-in-the-2020-presidential-election-68c723a5-102b-4fcd-836b-5f3c43efa525.png"
    },
    {
      "id": "48",
      "name": "How many confirmed Coronavirus cases will there be at EOY in the USA?",
      "bid": 0.0,
      "ask": 1.0,
      "spread": 200.0,
      "volume_24h": 0.0,
      "volume_7d": 0.0,
      "liquidity": 1.937475,
      "image": "https://polymarket-upload.s3.us-east-2.amazonaws.com/how-many-confirmed-coronavirus-cases-will-there-be-at-eoy-in-the-usa-3ad2df05-e3cd-48bb-aa79-6a399bacea7d.png"
    },
    {
      "id": "56",
      "name": "Who will win the 2020 MLB World Series?",
      "bid": 0.0,
      "ask": 1.0,
      "spread": 200.0,
      "volume_24h": 0.0,
      "volume_7d": 0.0,
      "liquidity": 0.0,
      "image": "https://polymarket-upload.s3.us-east-2.amazonaws.com/who-will-win-the-2020-mlb-world-series-042bafda-3ed2-4aa2-80d0-f957bb7b04c9.png"
    },
    {
      "id": "57",
      "name": "Will Dharma\u2019s Phase 1 Retroactive UNI Distribution proposal pass?",
      "bid": 0.0,
      "ask": 1.0,
      "spread": 200.0,
      "volume_24h": 0.0,
      "volume_7d": 0.0,
      "liquidity": 0.0,
      "image": "https://polymarket-upload.s3.us-east-2.amazonaws.com/will-dharmas-phase-1-retroactive-uni-distribution-proposal-pass-d44e2a5f-e0b7-4d37-a03b-169d6b56797c.png"
    },
    {
      "id": "59",
      "name": "Will there be a federal charge filed against Hunter Biden before 2021?",
      "bid": 0.0,
      "ask": 1.0,
      "spread": 200.0,
      "volume_24h": 0.0,
      "volume_7d": 0.0,
      "liquidity": 0.13149,
      "image": "https://polymarket-upload.s3.us-east-2.amazonaws.com/will-there-be-a-federal-charge-filed-against-hunter-biden-before-2021-13153b30-c6d7-4900-8a45-f4fd58c233fa.png"
    },
    {
      "id": "63",
      "name": "Will BTC break $15k before 2021?",
      "bid": 0.0,
      "ask": 1.0,
      "spread": 200.0,
      "volume_24h": 0.0,
      "volume_7d": 0.0,
      "liquidity": 0.0,
      "image": "https://polymarket-upload.s3.us-east-2.amazonaws.com/will-btc-break-15k-before-2021-127cae90-e9fb-4fcd-a8db-5dbe657a50de.png"
    },
    {
      "id": "64",
      "name": "Will Khabib win his UFC 254 Fight?",
      "bid": 0.0,
      "ask": 1.0,
      "spread": 200.0,
      "volume_24h": 0.0,
      "volume_7d": 0.0,
      "liquidity": 0.0,
      "image": "https://polymarket-upload.s3.us-east-2.amazonaws.com/will-khabib-win-his-ufc-254-fight-daf2f440-1745-4acb-9b81-c8203f687d40.png"
    },
    {
      "id": "65",
      "name": "Will 538 outperform The Economist in forecasting the 2020 Presidential Election?",
      "bid": 0.0,
      "ask": 1.0,
      "spread": 200.0,
      "volume_24h": 0.0,
      "volume_7d": 0.0,
      "liquidity": 0.0,
      "image": "https://polymarket-upload.s3.us-east-2.amazonaws.com/will-538-outperform-the-economist-in-forecasting-the-2020-presidential-election-cb3516e6-e193-4573-9f60-bb56886af14e.png"
    },
    {
      "id": "66",
      "name": "Who will win the 2020 League of Legends World Championship?",
      "bid": 0.0,
      "ask": 1.0,
      "spread": 200.0,
      "volume_24h": 0.0,
      "volume_7d": 0.0,
      "liquidity": 0.0,
      "image": "https://polymarket-upload.s3.us-east-2.amazonaws.com/who-will-win-the-2020-league-of-legends-world-championship-4f86893c-dfea-4546-907e-ace404bcece8.png"
    },
    {
      "id": "67",
      "name": "Which party will win Pennsylvania in the 2020 presidential election?",
      "bid": 0.0,
      "ask": 1.0,
      "spread": 200.0,
      "volume_24h": 0.0,
      "volume_7d": 0.0,
      "liquidity": 0.0,
      "image": "https://polymarket-upload.s3.us-east-2.amazonaws.com/which-party-will-win-pennsylvania-in-the-2020-presidential-election-a5ee99f0-4a1f-41ef-9837-c18b90dc537a.png"
    },
    {
      "id": "69",
      "name": "Which party will win Texas in the 2020 presidential election?",
      "bid": 0.0,
      "ask": 1.0,
      "spread": 200.0,
      "volume_24h": 0.0,
      "volume_7d": 0.0,
      "liquidity": 0.0,
      "image": "https://polymarket-upload.s3.us-east-2.amazonaws.com/which-party-will-win-texas-in-the-2020-presidential-election-30f7ac09-9c52-4645-94b4-dd70139326aa.png"
    },
    {
      "id": "70",
      "name": "Which party will win North Carolina in the 2020 presidential election?",
      "bid": 0.0,
      "ask": 1.0,
      "spread": 200.0,
      "volume_24h": 0.0,
      "volume_7d": 0.0,
      "liquidity": 0.0,
      "image": "https://polymarket-upload.s3.us-east-2.amazonaws.com/which-party-will-win-north-carolina-in-the-2020-presidential-election-a453bf71-3aec-418d-8f4c-2001dd92ed69.png"
    },
    {
      "id": "71",
      "name": "Which party will win Georgia in the 2020 presidential election?",
      "bid": 0.0,
      "ask": 1.0,
      "spread": 200.0,
      "volume_24h": 0.0,
      "volume_7d": 0.0,
      "liquidity": 0.0,
      "image": "https://polymarket-upload.s3.us-east-2.amazonaws.com/which-party-will-win-georgia-in-the-2020-presidential-election-d5626abd-fa99-45bd-8ecd-83c510ba7c46.png"
    },
    {
      "id": "72",
      "name": "Which party will win Arizona in the 2020 Presidential Election?",
      "bid": 0.0,
      "ask": 1.0,
      "spread": 200.0,
      "volume_24h": 0.0,
      "volume_7d": 0.0,
      "liquidity": 5.470261,
      "image": "https://polymarket-upload.s3.us-east-2.amazonaws.com/which-party-will-win-arizona-in-the-2020-presidential-election-0a8959e1-0603-43fd-ac5e-95ea3952c900.png"
    },
    {
      "id": "73",
      "name": "Will Donald Trump tweet announcing that he won the election before November 5th 2020?",
      "bid": 0.0,
      "ask": 1.0,
      "spread": 200.0,
      "volume_24h": 0.0,
      "volume_7d": 0.0,
      "liquidity": 3.295904,
      "image": "https://polymarket-upload.s3.us-east-2.amazonaws.com/will-donald-trump-tweet-announcing-that-he-won-the-election-before-november-5th-2020-88d84ce3-6bef-4998-be98-7ee28efe6cbc.png"
    },
    {
      "id": "74",
      "name": "Will the Associated Press publish a tweet calling the 2020 US presidential election before November 6?",
      "bid": 0.0,
      "ask": 1.0,
      "spread": 200.0,
      "volume_24h": 0.0,
      "volume_7d": 0.0,
      "liquidity": 0.0,
      "image": "https://polymarket-upload.s3.us-east-2.amazonaws.com/will-the-associated-press-publish-a-tweet-calling-the-2020-us-presidential-election-before-november-6-0e9f7c02-54cc-4d2e-af33-970073868261.png"
    },
    {
      "id": "75",
      "name": "Will the Ethereum 2.0 Genesis Event happen successfully on December 1st, 2020?",
      "bid": 0.0,
      "ask": 1.0,
      "spread": 200.0,
      "volume_24h": 0.0,
      "volume_7d": 0.0,
      "liquidity": 7.877976,
      "image": "https://polymarket-upload.s3.us-east-2.amazonaws.com/will-the-ethereum-20-genesis-event-happen-successfully-on-december-1st-2020-69a3535d-c23f-4e85-8594-6ef4526b3fb9.png"
    },
    {
      "id": "76",
      "name": "Will $BTC break $20k before 2021?",
      "bid": 0.0,
      "ask": 1.0,
      "spread": 200.0,
      "volume_24h": 0.0,
      "volume_7d": 0.0,
      "liquidity": 1170.706736,
      "image": "https://polymarket-upload.s3.us-east-2.amazonaws.com/will-btc-break-20k-before-2021-30270206-1bca-4add-8b66-21ec250f57c7.png"
    },
    {
      "id": "77",
      "name": "Will Donald Trump formally concede the 2020 US Election before December 1st, 2020?",
      "bid": 0.0,
      "ask": 1.0,
      "spread": 200.0,
      "volume_24h": 0.0,
      "volume_7d": 0.0,
      "liquidity": 8688.076983,
      "image": "https://polymarket-upload.s3.us-east-2.amazonaws.com/will-donald-trump-formally-concede-the-2020-us-election-before-december-1st-2020-25759491-ae8d-425c-9bde-9c900cd9a911.png"
    },
    {
      "id": "78",
      "name": "Will LaMelo Ball be the first pick in the 2020 NBA draft?",
      "bid": 0.0,
      "ask": 1.0,
      "spread": 200.0,
      "volume_24h": 0.0,
      "volume_7d": 0.0,
      "liquidity": 0.0,
      "image": "https://polymarket-upload.s3.us-east-2.amazonaws.com/will-lamelo-ball-be-the-first-pick-in-the-2020-nba-draft-af941394-e1fd-4a89-a99f-132e80018aef.png"
    },
    {
      "id": "86",
      "name": "Will Kanye West release a new studio album before 2021?",
      "bid": 0.0,
      "ask": 1.0,
      "spread": 200.0,
      "volume_24h": 0.0,
      "volume_7d": 0.0,
      "liquidity": 0.0,
      "image": "https://polymarket-upload.s3.us-east-2.amazonaws.com/will-kanye-west-release-a-new-studio-album-before-2021-b09d110f-4f8f-46eb-91dc-f2c3f36956df.png"
    },
    {
      "id": "87",
      "name": "Will Donald Trump attend Joe Biden\u2019s inauguration ceremony in person?",
      "bid": 0.0,
      "ask": 1.0,
      "spread": 200.0,
      "volume_24h": 0.0,
      "volume_7d": 0.0,
      "liquidity": 54.798207,
      "image": "https://polymarket-upload.s3.us-east-2.amazonaws.com/will-donald-trump-attend-joe-bidens-inauguration-ceremony-in-person-f5ea57ac-72eb-450b-9361-8aaee239a500.png"
    },
    {
      "id": "92",
      "name": "What will Airbnb's market cap be at close on its 1st day publicly trading?",
      "bid": 0.0,
      "ask": 1.0,
      "spread": 200.0,
      "volume_24h": 0.0,
      "volume_7d": 0.0,
      "liquidity": 0.0,
      "image": "https://polymarket-upload.s3.us-east-2.amazonaws.com/what-will-airbnbs-market-cap-be-at-close-on-its-1st-day-publicly-trading-0fe524ff-c88f-4f78-8b07-87bb99bbfbab.png"
    },
    {
      "id": "93",
      "name": "Will Donald Trump be inaugurated for his second term as President of the USA on Inauguration Day, January 20th, 2021?",
      "bid": 0.0,
      "ask": 1.0,
      "spread": 200.0,
      "volume_24h": 0.0,
      "volume_7d": 0.0,
      "liquidity": 43.468918,
      "image": "https://polymarket-upload.s3.us-east-2.amazonaws.com/will-donald-trump-be-inaugurated-for-his-second-term-as-president-of-the-usa-on-inauguration-day-january-20th-2021-9ed44688-a501-4d18-aaca-18d134cf5319.png"
    },
    {
      "id": "96",
      "name": "Will Trump win any of Pennsylvania, Arizona or Georgia?",
      "bid": 0.0,
      "ask": 1.0,
      "spread": 200.0,
      "volume_24h": 0.0,
      "volume_7d": 0.0,
      "liquidity": 2.945378,
      "image": "https://polymarket-upload.s3.us-east-2.amazonaws.com/will-trump-win-any-of-pennsylvania-arizona-or-georgia-9651de56-82f9-4dae-aaef-d6c7097601a9.png"
    },
    {
      "id": "97",
      "name": "Will any art piece on Superrare sell for more than $100k before 2021?",
      "bid": 0.0,
      "ask": 1.0,
      "spread": 200.0,
      "volume_24h": 0.0,
      "volume_7d": 0.0,
      "liquidity": 5.6e-05,
      "image": ""
    },
    {
      "id": "98",
      "name": "Will Uniswap v3 launch before 2021?",
      "bid": 0.0,
      "ask": 1.0,
      "spread": 200.0,
      "volume_24h": 0.0,
      "volume_7d": 0.0,
      "liquidity": 0.0,
      "image": ""
    },
    {
      "id": "99",
      "name": "Will the Seahawks or the Rams win their week 10 NFL matchup?",
      "bid": 0.0,
      "ask": 1.0,
      "spread": 200.0,
      "volume_24h": 0.0,
      "volume_7d": 0.0,
      "liquidity": 0.0,
      "image": "https://polymarket-upload.s3.us-east-2.amazonaws.com/will-the-seahawks-or-the-rams-win-their-week-10-nfl-matchup-1af80869-e4e7-4a1a-88e2-fbbc067915f0.png"
    },
    {
      "id": "100",
      "name": "Will indoor dining be prohibited in NYC at any point before 2021?",
      "bid": 0.0,
      "ask": 1.0,
      "spread": 200.0,
      "volume_24h": 0.0,
      "volume_7d": 0.0,
      "liquidity": 3.1e-05,
      "image": "https://polymarket-upload.s3.us-east-2.amazonaws.com/will-indoor-dining-be-prohibited-in-nyc-at-any-point-before-2021-a47cc6fe-dd40-41e9-9325-69fc463114b2.png"
    },
    {
      "id": "101",
      "name": "Will Pfizer's COVID-19 vaccine be the first to receive FDA approval or Emergency Use Authorization (EUA)?",
      "bid": 0.0,
      "ask": 1.0,
      "spread": 200.0,
      "volume_24h": 0.0,
      "volume_7d": 0.0,
      "liquidity": 0.0,
      "image": "https://polymarket-upload.s3.us-east-2.amazonaws.com/will-pfizers-covid-19-vaccine-be-the-first-to-receive-fda-approval-or-emergency-use-authorization-eua-e2960869-3cd3-4083-a9b2-dc92453ffd4c.png"
    },
    {
      "id": "102",
      "name": "Will Sushiswap have more TVL than Uniswap at any time before November 24th, according to DefiPulse?",
      "bid": 0.0,
      "ask": 1.0,
      "spread": 200.0,
      "volume_24h": 0.0,
      "volume_7d": 0.0,
      "liquidity": 0.0,
      "image": ""
    },
    {
      "id": "103",
      "name": "Will $BTC break $20k before Thanksgiving?",
      "bid": 0.0,
      "ask": 1.0,
      "spread": 200.0,
      "volume_24h": 0.0,
      "volume_7d": 0.0,
      "liquidity": 0.0,
      "image": "https://polymarket-upload.s3.us-east-2.amazonaws.com/will-btc-break-20k-before-thanksgiving-2089d738-72f4-42eb-95f4-21e80fa8f4b6.png"
    },
    {
      "id": "105",
      "name": "Will Liverpool beat Leicester City in their Matchday 9 game?",
      "bid": 0.0,
      "ask": 1.0,
      "spread": 200.0,
      "volume_24h": 0.0,
      "volume_7d": 0.0,
      "liquidity": 0.0,
      "image": "https://polymarket-upload.s3.us-east-2.amazonaws.com/will-liverpool-beat-leicester-city-in-their-matchday-9-game-68d7864a-3202-4def-bfda-6e939d5750b6.png"
    },
    {
      "id": "107",
      "name": "Will Deiveson Figueiredo win his UFC 255 match?",
      "bid": 0.0,
      "ask": 1.0,
      "spread": 200.0,
      "volume_24h": 0.0,
      "volume_7d": 0.0,
      "liquidity": 0.0,
      "image": "https://polymarket-upload.s3.us-east-2.amazonaws.com/will-deiveson-figueiredo-win-his-ufc-255-match-5c9258a6-89c5-4b19-ab25-f7f4c9e2df1b.png"
    },
    {
      "id": "108",
      "name": "What will the average sale price of the Jordan 1 Mocha on StockX be on Christmas Day?",
      "bid": 0.0,
      "ask": 1.0,
      "spread": 200.0,
      "volume_24h": 0.0,
      "volume_7d": 0.0,
      "liquidity": 0.0,
      "image": ""
    },
    {
      "id": "109",
      "name": "Will Trump Pardon Himself in His First Term?",
      "bid": 0.0,
      "ask": 1.0,
      "spread": 200.0,
      "volume_24h": 0.0,
      "volume_7d": 0.0,
      "liquidity": 99.338559,
      "image": "https://polymarket-upload.s3.us-east-2.amazonaws.com/will-trump-pardon-himself-in-his-first-term-670f4ada-4a6c-44b0-8a88-d08f01de17d9.png"
    },
    {
      "id": "110",
      "name": "Which party will win the U.S. Senate runoff in Georgia? (Ossoff - D vs. Perdue - R)",
      "bid": 0.0,
      "ask": 1.0,
      "spread": 200.0,
      "volume_24h": 0.0,
      "volume_7d": 0.0,
      "liquidity": 0.0,
      "image": "https://polymarket-upload.s3.us-east-2.amazonaws.com/which-party-will-win-the-us-senate-runoff-in-georgia-ossoff-d-vs-perdue-r-26c00745-ec9a-4694-9b68-8665ed469ce6.png"
    },
    {
      "id": "111",
      "name": "Which party will win the U.S. Senate special election in Georgia? (Loeffler - R vs Warnock - D)",
      "bid": 0.0,
      "ask": 1.0,
      "spread": 200.0,
      "volume_24h": 0.0,
      "volume_7d": 0.0,
      "liquidity": 45.370082,
      "image": "https://polymarket-upload.s3.us-east-2.amazonaws.com/which-party-will-win-the-us-senate-special-election-in-georgia-loeffler-r-vs-warnock-d-a1813eba-34cf-4a6a-bc81-c73c28285ed2.png"
    },
    {
      "id": "114",
      "name": "Will Coinbase reach #1 in the Finance category on the US iOS App Store before 2021?",
      "bid": 0.0,
      "ask": 1.0,
      "spread": 200.0,
      "volume_24h": 0.0,
      "volume_7d": 0.0,
      "liquidity": 0.0,
      "image": ""
    },
    {
      "id": "115",
      "name": "Superbowl 55: Kansas City Chiefs vs Tampa Bay Buccaneers",
      "bid": 0.0,
      "ask": 1.0,
      "spread": 200.0,
      "volume_24h": 0.0,
      "volume_7d": 0.0,
      "liquidity": 40.005841,
      "image": "https://polymarket-upload.s3.us-east-2.amazonaws.com/superbowl-55-kansas-city-chiefs-vs-tampa-bay-buccaneers-cda32a99-18c4-414d-95e0-184c7e597a6d.png"
    },
    {
      "id": "119",
      "name": "Will Jake Paul win his boxing match against Nate Robinson?",
      "bid": 0.0,
      "ask": 1.0,
      "spread": 200.0,
      "volume_24h": 0.0,
      "volume_7d": 0.0,
      "liquidity": 0.0,
      "image": "https://polymarket-upload.s3.us-east-2.amazonaws.com/will-jake-paul-win-his-boxing-match-against-nate-robinson-ccf950df-b199-472c-a00d-efe8b7b16d78.png"
    },
    {
      "id": "120",
      "name": "Will Mike Tyson win his boxing match against Roy Jones Jr?",
      "bid": 0.0,
      "ask": 1.0,
      "spread": 200.0,
      "volume_24h": 0.0,
      "volume_7d": 0.0,
      "liquidity": 1.8e-05,
      "image": "https://polymarket-upload.s3.us-east-2.amazonaws.com/will-mike-tyson-win-his-boxing-match-against-roy-jones-jr-485c4a4f-8e7a-406e-999a-7e73c4815881.png"
    },
    {
      "id": "1499",
      "name": "Will Donald Trump join Parler before Inauguration Day?",
      "bid": 0.0,
      "ask": 1.0,
      "spread": 200.0,
      "volume_24h": 0.0,
      "volume_7d": 0.0,
      "liquidity": 0.0,
      "image": ""
    },
    {
      "id": "1500",
      "name": "What will the average sale price of a PS5 be on StockX on Christmas Day?",
      "bid": 0.0,
      "ask": 1.0,
      "spread": 200.0,
      "volume_24h": 0.0,
      "volume_7d": 0.0,
      "liquidity": 0.0,
      "image": ""
    },
    {
      "id": "1547",
      "name": "What rating will theneedledrop give Drake\u2019s \"Certified Lover Boy\"?",
      "bid": 0.0,
      "ask": 1.0,
      "spread": 200.0,
      "volume_24h": 0.0,
      "volume_7d": 0.0,
      "liquidity": 1e-05,
      "image": "https://polymarket-upload.s3.us-east-2.amazonaws.com/what-rating-will-theneedledrop-give-drakes-certified-lover-boy-cea264db-0938-42d4-9bac-5bca6b6124aa.png"
    },
    {
      "id": "3339",
      "name": "Will Floyd Mayweather beat Logan Paul in their boxing exhibition match?",
      "bid": 0.0,
      "ask": 1.0,
      "spread": 200.0,
      "volume_24h": 0.0,
      "volume_7d": 0.0,
      "liquidity": 1.159156,
      "image": "https://polymarket-upload.s3.us-east-2.amazonaws.com/will-floyd-mayweather-beat-logan-paul-in-their-boxing-exhibition-match-a5a8f5cf-478c-4f01-94b6-ca582660b290.png"
    },
    {
      "id": "3971",
      "name": "Will Donald Trump pardon Julian Assange?",
      "bid": 0.0,
      "ask": 1.0,
      "spread": 200.0,
      "volume_24h": 0.0,
      "volume_7d": 0.0,
      "liquidity": 0.000121,
      "image": "https://polymarket-upload.s3.us-east-2.amazonaws.com/will-donald-trump-pardon-julian-assange-6e98da9c-65a0-4c2a-b604-e92a2bc396d9.png"
    },
    {
      "id": "5790",
      "name": "Will Playboi Carti release a new album before 2021?",
      "bid": 0.0,
      "ask": 1.0,
      "spread": 200.0,
      "volume_24h": 0.0,
      "volume_7d": 0.0,
      "liquidity": 0.0,
      "image": "https://polymarket-upload.s3.us-east-2.amazonaws.com/will-playboi-carti-release-a-new-album-before-2021-38740987-c158-4a0d-b19b-da07874a38fc.png"
    },
    {
      "id": "7715",
      "name": "Will Donald Trump pardon Ross Ulbricht?",
      "bid": 0.0,
      "ask": 1.0,
      "spread": 200.0,
      "volume_24h": 0.0,
      "volume_7d": 0.0,
      "liquidity": 0.0,
      "image": ""
    },
    {
      "id": "7716",
      "name": "Will Donald Trump pardon Edward Snowden?",
      "bid": 0.0,
      "ask": 1.0,
      "spread": 200.0,
      "volume_24h": 0.0,
      "volume_7d": 0.0,
      "liquidity": 0.0,
      "image": "https://polymarket-upload.s3.us-east-2.amazonaws.com/will-donald-trump-pardon-edward-snowden-d8bfe1ba-a975-4c0d-b415-9351b46fd430.png"
    },
    {
      "id": "7740",
      "name": "Will any Electoral College Certificates of Vote be formally challenged in Congress?",
      "bid": 0.0,
      "ask": 1.0,
      "spread": 200.0,
      "volume_24h": 0.0,
      "volume_7d": 0.0,
      "liquidity": 0.0,
      "image": "https://polymarket-upload.s3.us-east-2.amazonaws.com/will-any-electoral-college-certificates-of-vote-be-formally-challenged-in-congress-b876819f-1c7a-41b6-ab5b-1186c7af86db.png"
    },
    {
      "id": "7747",
      "name": "Which party will control the senate?",
      "bid": 0.0,
      "ask": 1.0,
      "spread": 200.0,
      "volume_24h": 0.0,
      "volume_7d": 0.0,
      "liquidity": 6.263726,
      "image": "https://polymarket-upload.s3.us-east-2.amazonaws.com/which-party-will-control-the-senate-7cde686b-e660-47b7-806c-83586d8d96c4.png"
    },
    {
      "id": "8938",
      "name": "Will ETH be above $1,500 on January 27th?",
      "bid": 0.0,
      "ask": 1.0,
      "spread": 200.0,
      "volume_24h": 0.0,
      "volume_7d": 0.0,
      "liquidity": 6.8e-05,
      "image": "https://polymarket-upload.s3.us-east-2.amazonaws.com/will-eth-be-above-1500-on-january-27th-3f8b01e8-50de-4b6e-9c9b-610929dbde96.png"
    },
    {
      "id": "8939",
      "name": "Will $BTC break $25k before March 1st?",
      "bid": 0.0,
      "ask": 1.0,
      "spread": 200.0,
      "volume_24h": 0.0,
      "volume_7d": 0.0,
      "liquidity": 6e-06,
      "image": "https://polymarket-upload.s3.us-east-2.amazonaws.com/will-btc-break-25k-before-march-1st-8b62175c-d973-48ba-b84c-36d07bdbbd45.png"
    },
    {
      "id": "10196",
      "name": "What will Coinbase\u2019s market cap be 1 week after it starts publicly trading?",
      "bid": 0.0,
      "ask": 1.0,
      "spread": 200.0,
      "volume_24h": 0.0,
      "volume_7d": 0.0,
      "liquidity": 61.074887,
      "image": "https://polymarket-upload.s3.us-east-2.amazonaws.com/what-will-coinbases-market-cap-be-1-week-after-it-starts-publicly-trading-8e93a380-2514-44f9-ac3f-f413c06c4804.png"
    },
    {
      "id": "11987",
      "name": "Will Tesla announce a Bitcoin purchase before March 1, 2021?",
      "bid": 0.0,
      "ask": 1.0,
      "spread": 200.0,
      "volume_24h": 0.0,
      "volume_7d": 0.0,
      "liquidity": 0.000168,
      "image": "https://polymarket-upload.s3.us-east-2.amazonaws.com/will-tesla-announce-a-bitcoin-purchase-before-march-1-2021-72ebc6d3-8cd5-4f5e-baad-69ba8819be6f.png"
    },
    {
      "id": "11988",
      "name": "Will Bitcoin or Tesla have a higher market cap on March 1, 2021?",
      "bid": 0.0,
      "ask": 1.0,
      "spread": 200.0,
      "volume_24h": 0.0,
      "volume_7d": 0.0,
      "liquidity": 2.687799,
      "image": "https://polymarket-upload.s3.us-east-2.amazonaws.com/will-bitcoin-or-tesla-have-a-higher-market-cap-on-march-1-2021-bb7ff199-c080-4d9e-a093-4c55b01ca013.png"
    },
    {
      "id": "11991",
      "name": "Will 100 million people have received a dose of an approved COVID-19 vaccine in the US by April 1, 2021?",
      "bid": 0.0,
      "ask": 1.0,
      "spread": 200.0,
      "volume_24h": 0.0,
      "volume_7d": 0.0,
      "liquidity": 83.003653,
      "image": "https://polymarket-upload.s3.us-east-2.amazonaws.com/will-100-million-people-have-received-a-dose-of-an-approved-covid-19-vaccine-in-the-us-by-april-1-2021-c7e6c5f6-10cd-4807-8be2-df1067dacd1d.png"
    },
    {
      "id": "12015",
      "name": "Will President Trump be suspended from Twitter before April 1, 2021?",
      "bid": 0.0,
      "ask": 1.0,
      "spread": 200.0,
      "volume_24h": 0.0,
      "volume_7d": 0.0,
      "liquidity": 1e-06,
      "image": "https://polymarket-upload.s3.us-east-2.amazonaws.com/will-president-trump-be-suspended-from-twitter-before-april-1-2021-6cf3acba-33dc-474c-b7d3-52984a44499c.png"
    },
    {
      "id": "12016",
      "name": "Will Andrew Yang win the Democratic primary for Mayor of New York City in 2021?",
      "bid": 0.0,
      "ask": 1.0,
      "spread": 200.0,
      "volume_24h": 0.0,
      "volume_7d": 0.0,
      "liquidity": 2045.016719,
      "image": "https://polymarket-upload.s3.us-east-2.amazonaws.com/will-andrew-yang-win-the-democratic-primary-for-mayor-of-new-york-city-in-2021-d0d00220-1de4-4534-8f87-37bcf857362d.png"
    },
    {
      "id": "12017",
      "name": "Will Kim Kardashian or Kanye West file for divorce before March 1, 2021?",
      "bid": 0.0,
      "ask": 1.0,
      "spread": 200.0,
      "volume_24h": 0.0,
      "volume_7d": 0.0,
      "liquidity": 962.430075,
      "image": "https://polymarket-upload.s3.us-east-2.amazonaws.com/will-kim-kardashian-or-kanye-west-file-for-divorce-before-march-1-2021-213d38ed-be04-4b6c-b1a0-c5511f40dcdc.png"
    },
    {
      "id": "12576",
      "name": "Will Coinbase delist Ripple (XRP) before they begin publicly trading?",
      "bid": 0.0,
      "ask": 1.0,
      "spread": 200.0,
      "volume_24h": 0.0,
      "volume_7d": 0.0,
      "liquidity": 9.3e-05,
      "image": ""
    },
    {
      "id": "13107",
      "name": "Will Joe Biden be inaugurated as President of the USA on January 20th, 2021?",
      "bid": 0.0,
      "ask": 1.0,
      "spread": 200.0,
      "volume_24h": 0.0,
      "volume_7d": 0.0,
      "liquidity": 40.886614,
      "image": ""
    },
    {
      "id": "18286",
      "name": "Will Donald Trump pardon a family member before Inauguration Day?",
      "bid": 0.0,
      "ask": 1.0,
      "spread": 200.0,
      "volume_24h": 0.0,
      "volume_7d": 0.0,
      "liquidity": 0.0,
      "image": "https://polymarket-upload.s3.us-east-2.amazonaws.com/will-donald-trump-pardon-a-family-member-before-inauguration-day-9dd5a564-8f57-4fc5-8aae-f005bb5ce33b.png"
    },
    {
      "id": "25367",
      "name": "Will $BTC break $50k before April 1st, 2021?",
      "bid": 0.0,
      "ask": 1.0,
      "spread": 200.0,
      "volume_24h": 0.0,
      "volume_7d": 0.0,
      "liquidity": 238.094982,
      "image": "https://polymarket-upload.s3.us-east-2.amazonaws.com/will-btc-break-50k-before-april-1st-2021-6dd810fc-112b-419b-974e-cf6746ec946b.png"
    },
    {
      "id": "29908",
      "name": "Will the Titans or the Ravens win their January 10th NFL Wild Card matchup?",
      "bid": 0.0,
      "ask": 1.0,
      "spread": 200.0,
      "volume_24h": 0.0,
      "volume_7d": 0.0,
      "liquidity": 0.0,
      "image": "https://polymarket-upload.s3.us-east-2.amazonaws.com/will-the-titans-or-the-ravens-win-their-january-10th-nfl-wild-card-matchup-380a95db-9bb1-435e-8b25-ee097aff91ef.png"
    },
    {
      "id": "29919",
      "name": "Will Trump complete his first term?",
      "bid": 0.0,
      "ask": 1.0,
      "spread": 200.0,
      "volume_24h": 0.0,
      "volume_7d": 0.0,
      "liquidity": 3.3e-05,
      "image": "https://polymarket-upload.s3.us-east-2.amazonaws.com/will-trump-complete-his-first-term-1f0fad9b-c0be-4116-883f-b5733044444a.png"
    },
    {
      "id": "30941",
      "name": "Will Joe Biden be President of the USA on March 1, 2021?",
      "bid": 0.0,
      "ask": 1.0,
      "spread": 200.0,
      "volume_24h": 0.0,
      "volume_7d": 0.0,
      "liquidity": 0.104587,
      "image": "https://polymarket-upload.s3.us-east-2.amazonaws.com/will-joe-biden-be-president-of-the-usa-on-march-1-2021-d1992842-b5af-4b69-a313-9afefcff8651.png"
    },
    {
      "id": "31023",
      "name": "Who will the world's richest person be on February 27, 2021?",
      "bid": 0.0,
      "ask": 1.0,
      "spread": 200.0,
      "volume_24h": 0.0,
      "volume_7d": 0.0,
      "liquidity": 1723.058544,
      "image": "https://polymarket-upload.s3.us-east-2.amazonaws.com/who-will-the-worlds-richest-person-be-on-february-27-2021-d5eda5a0-281c-4f44-a722-1ebc45d2a847.png"
    },
    {
      "id": "31064",
      "name": "Will Donald Trump be impeached again before the end of his term?",
      "bid": 0.0,
      "ask": 1.0,
      "spread": 200.0,
      "volume_24h": 0.0,
      "volume_7d": 0.0,
      "liquidity": 3e-06,
      "image": "https://polymarket-upload.s3.us-east-2.amazonaws.com/will-donald-trump-be-impeached-again-before-the-end-of-his-term-5dcef99b-9632-42b8-9f72-cf18ff6d29b3.png"
    },
    {
      "id": "34767",
      "name": "Will an official Presidential inauguration take place in-person outside the US Capitol on January 20th, 2021?",
      "bid": 0.0,
      "ask": 1.0,
      "spread": 200.0,
      "volume_24h": 0.0,
      "volume_7d": 0.0,
      "liquidity": 0.0,
      "image": ""
    },
    {
      "id": "35974",
      "name": "Will the Senate convict Donald Trump on impeachment by April 29, 2021?",
      "bid": 0.0,
      "ask": 1.0,
      "spread": 200.0,
      "volume_24h": 0.0,
      "volume_7d": 0.0,
      "liquidity": 0.03717,
      "image": "https://polymarket-upload.s3.us-east-2.amazonaws.com/will-the-senate-convict-donald-trump-on-impeachment-by-april-29-2021-0e0c2f2e-89e5-46fd-b55a-a82ea3ef1948.png"
    },
    {
      "id": "35976",
      "name": "Will Joe Biden be officially inaugurated as President in-person outside the US capitol on January 20th, 2021?",
      "bid": 0.0,
      "ask": 1.0,
      "spread": 200.0,
      "volume_24h": 0.0,
      "volume_7d": 0.0,
      "liquidity": 2e-06,
      "image": "https://polymarket-upload.s3.us-east-2.amazonaws.com/will-joe-biden-be-officially-inaugurated-as-president-in-person-outside-the-us-capitol-on-january-20th-2021-72939c9c-2e2d-4e1b-95aa-f3f1e45e7b9e.png"
    },
    {
      "id": "35983",
      "name": "Will Donald Trump's Twitter account be active on March 1, 2021?",
      "bid": 0.0,
      "ask": 1.0,
      "spread": 200.0,
      "volume_24h": 0.0,
      "volume_7d": 0.0,
      "liquidity": 0.000147,
      "image": "https://polymarket-upload.s3.us-east-2.amazonaws.com/will-donald-trumps-twitter-account-be-active-on-march-1-2021-c08023ec-2cfe-452c-9782-4614cd4c2fdc.png"
    },
    {
      "id": "35988",
      "name": "$2000 stimulus checks by February 28, 2021?",
      "bid": 0.0,
      "ask": 1.0,
      "spread": 200.0,
      "volume_24h": 0.0,
      "volume_7d": 0.0,
      "liquidity": 0.000207,
      "image": "https://polymarket-upload.s3.us-east-2.amazonaws.com/2000-stimulus-checks-by-february-28-2021-1b1be249-b924-43b5-be46-82b9bf8edd1e.png"
    },
    {
      "id": "40935",
      "name": "Donald Trump federally charged by February 20th?",
      "bid": 0.0,
      "ask": 1.0,
      "spread": 200.0,
      "volume_24h": 0.0,
      "volume_7d": 0.0,
      "liquidity": 9708.484873,
      "image": "https://polymarket-upload.s3.us-east-2.amazonaws.com/donald-trump-federally-charged-by-february-20th-c728a06d-de3a-458f-9132-fde7de612ee5.png"
    },
    {
      "id": "40936",
      "name": "Will Conor McGregor win his UFC 257 match on January 23?",
      "bid": 0.0,
      "ask": 1.0,
      "spread": 200.0,
      "volume_24h": 0.0,
      "volume_7d": 0.0,
      "liquidity": 3.6e-05,
      "image": ""
    },
    {
      "id": "42114",
      "name": "Will the Rams or the Packers win their Jan 16th matchup?",
      "bid": 0.0,
      "ask": 1.0,
      "spread": 200.0,
      "volume_24h": 0.0,
      "volume_7d": 0.0,
      "liquidity": 0.0,
      "image": ""
    },
    {
      "id": "42115",
      "name": "Will the Buccaneers or the Saints win their Jan 17th matchup?",
      "bid": 0.0,
      "ask": 1.0,
      "spread": 200.0,
      "volume_24h": 0.0,
      "volume_7d": 0.0,
      "liquidity": 0.0,
      "image": ""
    },
    {
      "id": "42120",
      "name": "Will the Browns or the Chiefs win their Jan 17th matchup?",
      "bid": 0.0,
      "ask": 1.0,
      "spread": 200.0,
      "volume_24h": 0.0,
      "volume_7d": 0.0,
      "liquidity": 0.0,
      "image": "https://polymarket-upload.s3.us-east-2.amazonaws.com/will-the-browns-or-the-chiefs-win-their-jan-17th-matchup-b6184b3f-a305-4742-a202-a6517dfdc9c4.png"
    },
    {
      "id": "42121",
      "name": "Will the Ravens or Bills win their January 16th matchup?",
      "bid": 0.0,
      "ask": 1.0,
      "spread": 200.0,
      "volume_24h": 0.0,
      "volume_7d": 0.0,
      "liquidity": 0.0,
      "image": "https://polymarket-upload.s3.us-east-2.amazonaws.com/will-the-ravens-or-bills-win-their-january-16th-matchup-16d01cde-170b-4f3c-b24f-096c44eaef8a.png"
    },
    {
      "id": "42404",
      "name": "Will YFI total supply be greater than 30,000 by March 15th?",
      "bid": 0.0,
      "ask": 1.0,
      "spread": 200.0,
      "volume_24h": 0.0,
      "volume_7d": 0.0,
      "liquidity": 3.513259,
      "image": "https://polymarket-upload.s3.us-east-2.amazonaws.com/will-yfi-total-supply-be-greater-than-30000-by-march-15th-ba2e4e3c-7bcb-4ec5-b379-466ab4c73676.png"
    },
    {
      "id": "46924",
      "name": "How many tweets will @DonaldJTrumpJr post from Jan 18th to 25th?",
      "bid": 0.0,
      "ask": 1.0,
      "spread": 200.0,
      "volume_24h": 0.0,
      "volume_7d": 0.0,
      "liquidity": 5.5e-05,
      "image": "https://polymarket-upload.s3.us-east-2.amazonaws.com/how-many-tweets-will-donaldjtrumpjr-post-from-jan-18th-to-25th-ce73408b-bba7-4929-a847-4de1b911eeea.png"
    },
    {
      "id": "46928",
      "name": "Will the US have fewer than 50,000 new COVID-19 cases on any day before March 15, 2021?",
      "bid": 0.0,
      "ask": 1.0,
      "spread": 200.0,
      "volume_24h": 0.0,
      "volume_7d": 0.0,
      "liquidity": 1.277538,
      "image": "https://polymarket-upload.s3.us-east-2.amazonaws.com/will-the-us-have-fewer-than-50000-new-covid-19-cases-on-any-day-before-march-15-2021-985d03bc-9da1-4699-a2aa-5f85cf2b6f93.png"
    },
    {
      "id": "47250",
      "name": "Will Donald Trump be President of the USA on March 31, 2021?",
      "bid": 0.0,
      "ask": 1.0,
      "spread": 200.0,
      "volume_24h": 0.0,
      "volume_7d": 0.0,
      "liquidity": 1.442885,
      "image": "https://polymarket-upload.s3.us-east-2.amazonaws.com/will-donald-trump-be-president-of-the-usa-on-march-31-2021-203a1aae-bc39-494c-8474-1b0282100bcf.png"
    },
    {
      "id": "48678",
      "name": "Will the Green Bay Packers or the Tampa Bay Buccaneers win the NFC Championship?",
      "bid": 0.0,
      "ask": 1.0,
      "spread": 200.0,
      "volume_24h": 0.0,
      "volume_7d": 0.0,
      "liquidity": 0.004038,
      "image": ""
    },
    {
      "id": "48681",
      "name": "Will the Buffalo Bills or the Kansas City Chiefs win the AFC Championship?",
      "bid": 0.0,
      "ask": 1.0,
      "spread": 200.0,
      "volume_24h": 0.0,
      "volume_7d": 0.0,
      "liquidity": 0.00385,
      "image": ""
    },
    {
      "id": "57333",
      "name": "Will DeFi Dominance on CoinGecko be above 10% on March 15, 2021?",
      "bid": 0.0,
      "ask": 1.0,
      "spread": 200.0,
      "volume_24h": 0.0,
      "volume_7d": 0.0,
      "liquidity": 1871.70284,
      "image": ""
    },
    {
      "id": "57337",
      "name": "How many Senators will vote to convict Donald Trump on incitement by March 1?",
      "bid": 0.0,
      "ask": 1.0,
      "spread": 200.0,
      "volume_24h": 0.0,
      "volume_7d": 0.0,
      "liquidity": 0.812904,
      "image": "https://polymarket-upload.s3.us-east-2.amazonaws.com/how-many-senators-will-vote-to-convict-donald-trump-on-incitement-by-march-1-a21a2e3c-5e68-440b-9c34-eb1dd83faf3e.png"
    }
  ],
  "whales": []
}